bamboolean/__init__.py
bamboolean/ast.py
bamboolean/exceptions.py
bamboolean/factories.py
bamboolean/interpreter.py
bamboolean/lexer.py
bamboolean/node_visitor.py
bamboolean/parser.py
bamboolean/tokens.py
bamboolean/walkers.py
bamboolean/tests/__init__.py
bamboolean/tests/fixtures.py
bamboolean/tests/test_interpreter.py
bamboolean/tests/test_lexer.py
bamboolean/tests/test_normalize.py
bamboolean/tests/test_parser.py
bamboolean/tests/test_vars_extractor.py
bamboolean/tests/test_walkers.py
bamboolean/walkers/__init__.py
bamboolean/walkers/normalize.py
bamboolean/walkers/vars_extractor.py
bamboolean-0.4.0.dist-info/LICENSE
bamboolean-0.4.0.dist-info/METADATA
bamboolean-0.4.0.dist-info/WHEEL
bamboolean-0.4.0.dist-info/top_level.txt
bamboolean-0.4.0.dist-info/RECORD
