Metadata-Version: 2.1
Name: bamboolean
Version: 0.4.0
Summary: Interpreter of Boolean Logic Language
Home-page: https://github.com/qedsoftware/bamboolean
Author: Quantitative Engineering Design Inc.
Author-email: info@qed.ai
License: MIT
Keywords: boolean logic interpreter
Platform: UNKNOWN
Classifier: Development Status :: 3 - Alpha
Classifier: Intended Audience :: Developers
Classifier: Topic :: Software Development :: Interpreters
Classifier: License :: OSI Approved :: MIT License
Classifier: Programming Language :: Python :: 3
Classifier: Programming Language :: Python :: 3.4
Classifier: Programming Language :: Python :: 3.5
Classifier: Programming Language :: Python :: 3.6
